douyin_api/__init__.py
douyin_api/_version.py
douyin_api/api.py
douyin_api/exception.py
douyin_api/tool.py
douyin_api/utils.py
douyin_api-0.1.10.dist-info/METADATA
douyin_api-0.1.10.dist-info/WHEEL
douyin_api-0.1.10.dist-info/top_level.txt
douyin_api-0.1.10.dist-info/RECORD
